ws/__init__.py
ws/connection.py
ws/server.py
websocket_server_lib-0.0.3.dist-info/LICENSE.txt
websocket_server_lib-0.0.3.dist-info/METADATA
websocket_server_lib-0.0.3.dist-info/WHEEL
websocket_server_lib-0.0.3.dist-info/top_level.txt
websocket_server_lib-0.0.3.dist-info/RECORD
