Metadata-Version: 2.1
Name: websocket-server-lib
Version: 0.0.3
Summary: Library for websocket support in Python
Author: Rohan Julka
Author-email: Rohan Julka <rohanjulka19@gmail.com>
Project-URL: Homepage, https://github.com/x22205993/ws-server-python.git
License-File: LICENSE.txt
